{"0":"64 people are registered, including...","1":"Sharon O'Hara","2":"Debra Fagan","3":"David Fischer","4":"Nancy Price","5":"James Ellis","6":"Glenn Iverson","7":"Susan Eslick","8":"Devi Yorty","9":"Anna Nicotera","10":"Brenna Neal","11":"Yelena McElwain","12":"Mary Camacho","13":"Erica Wheeler","14":"Andrew Epstein","15":"Andrew Spruiell","16":"Alvin McBorrough","17":"Kealey Boyd","18":"Hannah Koch","19":"John Karner","20":"Douglas Hofmeister","21":"Jonson Berman","22":"Gregory Ellingson","23":"Allan Prochazka","24":"Jeannie DeMarinis"}